Metadata-Version: 1.0
Name: nli
Version: 0.4
Summary: natural language inference using tpu device
Home-page: UNKNOWN
Author: UNKNOWN
Author-email: UNKNOWN
License: UNKNOWN
Platform: UNKNOWN
